tns_cli/__init__.py
tns_cli/__main__.py
tns_cli/cli.py
tns_cli/client.py
tnscli-1.0.0.dist-info/licenses/LICENSE
tnscli-1.0.0.dist-info/METADATA
tnscli-1.0.0.dist-info/WHEEL
tnscli-1.0.0.dist-info/entry_points.txt
tnscli-1.0.0.dist-info/top_level.txt
tnscli-1.0.0.dist-info/RECORD
