Metadata-Version: 2.4
Name: tnscli
Version: 1.0.0
Summary: Command-line interface for TAO Name Service - Similar to btcli for Bittensor
Home-page: https://github.com/taonames/tns-cli
Author: TNS Team
Author-email: TNS Team <contact@taonames.com>
License: MIT
Project-URL: Homepage, https://github.com/taonames/tns-cli
Project-URL: Bug Reports, https://github.com/taonames/tns-cli/issues
Project-URL: Source, https://github.com/taonames/tns-cli
Keywords: tao,bittensor,blockchain,cli,domain-names,tns
Classifier: Development Status :: 4 - Beta
Classifier: Intended Audience :: Developers
Classifier: Intended Audience :: System Administrators
Classifier: Topic :: System :: Systems Administration
Classifier: Topic :: Software Development :: Libraries :: Python Modules
Classifier: License :: OSI Approved :: MIT License
Classifier: Programming Language :: Python :: 3
Classifier: Programming Language :: Python :: 3.7
Classifier: Programming Language :: Python :: 3.8
Classifier: Programming Language :: Python :: 3.9
Classifier: Programming Language :: Python :: 3.10
Classifier: Programming Language :: Python :: 3.11
Classifier: Programming Language :: Python :: 3.12
Classifier: Programming Language :: Python :: 3.13
Requires-Python: >=3.7
License-File: LICENSE
Requires-Dist: click==8.1.7
Requires-Dist: requests==2.31.0
Requires-Dist: substrate-interface==1.7.9
Requires-Dist: rich==13.7.0
Requires-Dist: python-dotenv==1.0.1
Dynamic: author
Dynamic: home-page
Dynamic: license-file
Dynamic: requires-python
